ebb_events/__init__.py
ebb_events/builders/event_builder.py
ebb_events/consumers/event_consumer.py
ebb_events/enums.py
ebb_events/event_payload_utils.py
ebb_events/event_schema.py
ebb_events/exceptions.py
ebb_events/field_constants.py
ebb_events-1.0.0.dist-info/LICENSE
ebb_events-1.0.0.dist-info/METADATA
ebb_events-1.0.0.dist-info/WHEEL
ebb_events-1.0.0.dist-info/RECORD
