Metadata-Version: 2.1
Name: ebb-events
Version: 1.0.0
Summary: Package for building and standardizing MQTT event messages.
Author: Ryan Bloom
Author-email: ryan.bloom@ebbcarbon.com
Requires-Python: >=3.10,<4.0
Classifier: Programming Language :: Python :: 3
Classifier: Programming Language :: Python :: 3.10
Classifier: Programming Language :: Python :: 3.11
Classifier: Programming Language :: Python :: 3.12
Requires-Dist: marshmallow (>=3.21.1,<4.0.0)
